db_automation/__init__.py
db_automation/mongo_crud.py
automationfordb-0.0.1.dist-info/LICENSE
automationfordb-0.0.1.dist-info/METADATA
automationfordb-0.0.1.dist-info/WHEEL
automationfordb-0.0.1.dist-info/top_level.txt
automationfordb-0.0.1.dist-info/RECORD
